canvas_data_utils
