Metadata-Version: 1.1
Name: pycanvasdata
Version: 0.0.3
Summary: Python utilities for working with Canvas Data
Home-page: UNKNOWN
Author: Kajigga dev
Author-email: kajigga+dev@gmail.com
License: MIT
Keywords: database canvasdata development
Platform: UNKNOWN
Classifier: Development Status :: 3 - Alpha
Classifier: Intended Audience :: Developers
Classifier: Topic :: Software Development :: Libraries :: Application Frameworks
Classifier: License :: OSI Approved :: MIT License
Classifier: Programming Language :: Python :: 2
Classifier: Programming Language :: Python :: 2.6
Classifier: Programming Language :: Python :: 2.7
Classifier: Programming Language :: Python :: 3
Classifier: Programming Language :: Python :: 3.2
Classifier: Programming Language :: Python :: 3.3
Classifier: Programming Language :: Python :: 3.4
Classifier: Programming Language :: Python :: 3.5
